stups/__init__.py
stups/__main__.py
stups/cli.py
stups-1.1.21.dist-info/DESCRIPTION.rst
stups-1.1.21.dist-info/METADATA
stups-1.1.21.dist-info/RECORD
stups-1.1.21.dist-info/WHEEL
stups-1.1.21.dist-info/entry_points.txt
stups-1.1.21.dist-info/metadata.json
stups-1.1.21.dist-info/top_level.txt
